flask_sso_saml/__init__.py
flask_sso_saml/_compat.py
flask_sso_saml/config.py
flask_sso_saml/ext.py
flask_sso_saml/proxies.py
flask_sso_saml/utils.py
flask_sso_saml/version.py
flask_sso_saml/views.py
flask_sso_saml-0.2.0.dist-info/AUTHORS.rst
flask_sso_saml-0.2.0.dist-info/LICENSE
flask_sso_saml-0.2.0.dist-info/METADATA
flask_sso_saml-0.2.0.dist-info/WHEEL
flask_sso_saml-0.2.0.dist-info/top_level.txt
flask_sso_saml-0.2.0.dist-info/RECORD
